{
  "carvers": {
    "air": [
      "minecraft:cave",
      "minecraft:canyon"
    ]
  },
  "creature_spawn_probability": 0.01,
  "downfall": 0.5,
  "effects": {
    "fog_color": 12638463,
    "mood_sound": {
      "block_search_extent": 8,
      "offset": 2,
      "sound": "minecraft:ambient.cave",
      "tick_delay": 6000
    },
    "sky_color": 7907327,
    "water_color": 4159204,
    "water_fog_color": 329011
  },
  "features": [
    [
      "the_winter_rescue:glacial/blue_ice",
      "the_winter_rescue:glacial/icicle",
      "the_winter_rescue:glacial/puddle"
    ],
    [
      "minecraft:lake_lava_underground",
      "minecraft:lake_lava_surface"
    ],
    [
      "minecraft:iceberg_packed",
      "minecraft:iceberg_blue",
      "minecraft:amethyst_geode"
    ],
    [
      "minecraft:monster_room",
      "minecraft:monster_room_deep"
    ],
    [
      "minecraft:blue_ice",
      "minecraft:ice_spike",
      "minecraft:ice_patch"
    ],
    [],
    [
      "minecraft:ore_gravel",
      "minecraft:ore_granite_lower",
      "minecraft:ore_diorite_lower",
      "minecraft:ore_andesite_lower",
      "minecraft:ore_tuff",
      "minecraft:ore_coal_lower",
      "minecraft:ore_iron_middle",
      "minecraft:ore_iron_small",
      "minecraft:ore_gold",
      "minecraft:ore_gold_lower",
      "minecraft:ore_redstone",
      "minecraft:ore_redstone_lower",
      "minecraft:ore_lapis",
      "minecraft:ore_lapis_buried",
      "minecraft:ore_copper",
      "minecraft:underwater_magma",
      "minecraft:disk_sand",
      "minecraft:disk_clay",
      "minecraft:disk_gravel"
    ],
    [],
    [],
    [
      "minecraft:glow_lichen",
      "minecraft:flower_default",
      "minecraft:patch_grass_badlands",
      "minecraft:brown_mushroom_normal",
      "minecraft:red_mushroom_normal"
    ],
    [
      "minecraft:freeze_top_layer"
    ]
  ],
  "has_precipitation": true,
  "spawn_costs": {},
  "spawners": {
    "ambient": [

    ],
    "axolotls": [],
    "creature": [
      {
        "type": "minecraft:polar_bear",
        "maxCount": 1,
        "minCount": 1,
        "weight": 1
      }
    ],
    "misc": [],
    "monster": [

    ],
    "underground_water_creature": [
      {
        "type": "minecraft:glow_squid",
        "maxCount": 1,
        "minCount": 1,
        "weight": 1
      }
    ],
    "water_ambient": [],
    "water_creature": []
  },
  "temperature": 0
}